xlum/__init__.py
xlum/data/__init__.py
xlum/data/classes.py
xlum/data/enumerations.py
xlum/importer.py
xlum-0.0.9.dist-info/licenses/LICENSE
xlum-0.0.9.dist-info/WHEEL
xlum-0.0.9.dist-info/METADATA
xlum-0.0.9.dist-info/RECORD
