Metadata-Version: 2.4
Name: xlum
Version: 0.0.9
Summary: Python importer for the XLUM data exchange and archive format
Author: Steve Grehl, Sebastian Kreutzer
Author-email: Steve Grehl <research@steve-grehl.eu>
License-File: LICENSE
Classifier: Development Status :: 4 - Beta
Classifier: Intended Audience :: Education
Classifier: Topic :: File Formats
Classifier: Operating System :: OS Independent
Classifier: Programming Language :: Python :: 3
Classifier: Programming Language :: Python :: 3.9
Classifier: Programming Language :: Python :: 3.10
Classifier: Programming Language :: Python :: 3.11
Classifier: Programming Language :: Python :: 3.12
Classifier: Programming Language :: Python :: 3.13
Requires-Dist: lxml
Requires-Dist: pandas
Requires-Dist: requests
Requires-Dist: openpyxl
Requires-Dist: pytest>=8.4.1
Requires-Dist: certifi>=2025.8.3
Requires-Python: >=3.9
